{
  "title": "Make Heroine ga Oosugiru! @comic",
  "description": "### Thể loại\nRomance, Comedy, School Life, Slice of Life, Drama, Adaption\n\n## Tiêu đề\n- Tiếng Anh: Too Many Losing Heroines!\n- Tiếng Việt: Có Quá Nhiều Nữ Chính Thua Cuộc! @comic\n- Tiếng Nhật: 負けヒロインが多すぎる！@comic \n- Romanji: Make Heroine ga Oosugiru! @comic\n\n# Nội dung\n\n*Chuyển thể từ Light Novel cùng tên.\n\n“Hử? Cậu gọi ai là đồ thua cuộc cơ?”\n\nTôi, Kazuhiko Nukumizu, một nhân vật làm nền trong lớp, chứng kiến cảnh cô nàng nổi tiếng – Anna Yanami bị một nam sinh khác từ chối.\n\n“Dù cho cậu ấy đã từng nói bọn mình sẽ kết hôn đấy. Cậu có thấy cậu ấy quá đáng không?”\n\n“Cậu ấy nói thế vào lúc nào vậy?”\n\n“Hồi bọn tớ 4 hay 5 tuổi gì đó.”\n\nThế thì đâu có tính?\n\nCùng với cô nàng còn có những nữ chính thua cuộc khác như Remon Yakishio của Câu lạc bộ Điền kinh và Komari Chika từ Câu lạc bộ Văn học.\n\n“Nukumizu-kun nè, trên đời có hai loại con gái. Một là bạn thuở nhỏ, còn lại là đồ đàn bà giựt bồ.”\n\n“Vậy hả. Chà, một tuyên bố đầy táo bạo ha.”\n\nCó một loại vận mệnh rằng có những người chỉ thực sự toả sáng sau khi đã thua cuộc.\n\nNhững nữ chính thua cuộc—Bức màn câu chuyện tuổi mới lớn mang tên “Makein” sẽ lật mở ngay bây giờ!*\n\n**Credit to Miko lino from Hako (LN)**\n\n## Link:\n- Fanpage: [SAM Shelter](https://fb.com/samshelter18)\n- Mangadex: [Click here](https://mangadex.org/title/3da96505-f8e8-49d5-8c26-fbe4786a897f/make-heroine-ga-oosugiru-comic)",
  "artist": "Itachi",
  "author": "Amamori Takibi",
  "cover": "https://files.catbox.moe/2qwz78.png",
  "chapters": {
    "1": {
      "title": "Vol 1 - Lần Bại Trận #1 | Hello, Yanami Anna",
      "volume": "1",
      "last_updated": "1747534841",
      "groups": {
        "SAM Shelter": [
          "https://files.catbox.moe/juupxz.avif",
          "https://files.catbox.moe/8m5ool.avif",
          "https://files.catbox.moe/9aeewn.avif",
          "https://files.catbox.moe/wgaaz8.avif",
          "https://files.catbox.moe/sqbjat.avif",
          "https://files.catbox.moe/8yipd0.avif",
          "https://files.catbox.moe/ys2cgi.avif",
          "https://files.catbox.moe/3u3t1i.avif",
          "https://files.catbox.moe/w84fos.avif",
          "https://files.catbox.moe/xipi7p.avif",
          "https://files.catbox.moe/p7kmru.avif",
          "https://files.catbox.moe/8dcuhj.avif",
          "https://files.catbox.moe/isfx8g.avif",
          "https://files.catbox.moe/5nx3kk.avif",
          "https://files.catbox.moe/mofq3k.avif",
          "https://files.catbox.moe/h974us.avif",
          "https://files.catbox.moe/j3pqe8.avif",
          "https://files.catbox.moe/tvjlod.avif",
          "https://files.catbox.moe/cne3zm.avif",
          "https://files.catbox.moe/02ep5x.avif",
          "https://files.catbox.moe/ohrbup.avif",
          "https://files.catbox.moe/0n5yeh.avif",
          "https://files.catbox.moe/hnu8pc.avif",
          "https://files.catbox.moe/ff97l4.avif",
          "https://files.catbox.moe/6i0lek.avif",
          "https://files.catbox.moe/xkwi9o.avif",
          "https://files.catbox.moe/9aoumy.avif",
          "https://files.catbox.moe/n9880q.avif",
          "https://files.catbox.moe/c3eom0.avif",
          "https://files.catbox.moe/s4i85l.avif",
          "https://files.catbox.moe/tc5u25.avif"
        ]
      }
    },
    "2": {
      "title": "Vol 1 - Lần Bại Trận #2 | Phải Chăng Tôi Chỉ Là Một Nhân Vật Nền Khờ Khạo Ở Bên Cạnh Nữ Chính Thua Cuộc Khi Kết Truyện?",
      "volume": "2",
      "last_updated": "1747537143",
      "groups": {
        "SAM Shelter": [
          "https://files.catbox.moe/ska2wn.avif",
          "https://files.catbox.moe/yojsrp.avif",
          "https://files.catbox.moe/brj9ul.avif",
          "https://files.catbox.moe/ckwonz.avif",
          "https://files.catbox.moe/7sltzd.avif",
          "https://files.catbox.moe/igjiuu.avif",
          "https://files.catbox.moe/dzapcv.avif",
          "https://files.catbox.moe/ra2vnq.avif",
          "https://files.catbox.moe/su6yt0.avif",
          "https://files.catbox.moe/ee9bsd.avif",
          "https://files.catbox.moe/hxkvm0.avif",
          "https://files.catbox.moe/4kx93c.avif",
          "https://files.catbox.moe/xp5vv7.avif",
          "https://files.catbox.moe/m3uk1d.avif",
          "https://files.catbox.moe/182obf.avif",
          "https://files.catbox.moe/5ldxxi.avif",
          "https://files.catbox.moe/puosfn.avif",
          "https://files.catbox.moe/q6dihj.avif",
          "https://files.catbox.moe/glwkyy.avif",
          "https://files.catbox.moe/0q57e1.avif",
          "https://files.catbox.moe/nrcu90.avif",
          "https://files.catbox.moe/igy0hz.avif",
          "https://files.catbox.moe/kwl1cy.avif",
          "https://files.catbox.moe/u2km87.avif",
          "https://files.catbox.moe/1xomla.avif",
          "https://files.catbox.moe/4t8tgf.avif",
          "https://files.catbox.moe/4l42pg.avif",
          "https://files.catbox.moe/k6ydu7.avif",
          "https://files.catbox.moe/rswwyr.avif",
          "https://files.catbox.moe/n6dhzq.avif",
          "https://files.catbox.moe/ffj21r.avif",
          "https://files.catbox.moe/ayttia.avif",
          "https://files.catbox.moe/1aqcg5.avif",
          "https://files.catbox.moe/l6ij9w.avif",
          "https://files.catbox.moe/2vlxwq.avif",
          "https://files.catbox.moe/obblbm.avif",
          "https://files.catbox.moe/tj7rpz.avif",
          "https://files.catbox.moe/8i9csu.avif",
          "https://files.catbox.moe/xjq2nz.avif",
          "https://files.catbox.moe/uacyhz.avif",
          "https://files.catbox.moe/cqx9ip.avif",
          "https://files.catbox.moe/nl1k6v.avif",
          "https://files.catbox.moe/2z12iv.avif",
          "https://files.catbox.moe/npwm4y.avif",
          "https://files.catbox.moe/d9cjfu.avif",
          "https://files.catbox.moe/t2qz1w.avif",
          "https://files.catbox.moe/01wjeu.avif"
        ]
      }
    },
    "3": {
      "title": "Vol 1 - Lần Bại Trận #3 | Thanh Xuân Có Vị Quýt",
      "volume": "1",
      "last_updated": "1747537042",
      "groups": {
        "SAM Shelter": [
          "https://files.catbox.moe/dsk2us.avif",
          "https://files.catbox.moe/pt6shj.avif",
          "https://files.catbox.moe/je3hab.avif",
          "https://files.catbox.moe/bepnpx.avif",
          "https://files.catbox.moe/qmk8a2.avif",
          "https://files.catbox.moe/3c2o8o.avif",
          "https://files.catbox.moe/01wket.avif",
          "https://files.catbox.moe/r3s397.avif",
          "https://files.catbox.moe/o1rko0.avif",
          "https://files.catbox.moe/tfa9pf.avif",
          "https://files.catbox.moe/zl3urw.avif",
          "https://files.catbox.moe/nltzzp.avif",
          "https://files.catbox.moe/0vnev7.avif",
          "https://files.catbox.moe/t2uw01.avif",
          "https://files.catbox.moe/8qt25w.avif",
          "https://files.catbox.moe/vc6tzm.avif",
          "https://files.catbox.moe/k7maa2.avif",
          "https://files.catbox.moe/jx1f9w.avif",
          "https://files.catbox.moe/rd6m52.avif",
          "https://files.catbox.moe/f0xrkh.avif",
          "https://files.catbox.moe/8t7b36.avif",
          "https://files.catbox.moe/caur79.avif",
          "https://files.catbox.moe/1g3mcv.avif",
          "https://files.catbox.moe/m4d6kq.avif",
          "https://files.catbox.moe/7lp6s2.avif",
          "https://files.catbox.moe/ftqflj.avif",
          "https://files.catbox.moe/ilsolq.avif",
          "https://files.catbox.moe/upu6mv.avif",
          "https://files.catbox.moe/2d9u36.avif",
          "https://files.catbox.moe/pptxn7.avif",
          "https://files.catbox.moe/6v4zh9.avif"
        ]
      }
    },
    "4": {
      "title": "Vol 1 - Lần Bại Trận #4 | Nếu Đây Không Phải Bãi Mìn Thì Nên Gọi Là Gì? À Đúng Rồi, Là Nữ Chính Thua Cuộc",
      "volume": "1",
      "last_updated": "1747536697",
      "groups": {
        "SAM Shelter": [
          "https://files.catbox.moe/mgjgt0.avif",
          "https://files.catbox.moe/d2danc.avif",
          "https://files.catbox.moe/o8t0f7.avif",
          "https://files.catbox.moe/f3y8gt.avif",
          "https://files.catbox.moe/uwts5v.avif",
          "https://files.catbox.moe/ggc09a.avif",
          "https://files.catbox.moe/h3plw1.avif",
          "https://files.catbox.moe/5dgqif.avif",
          "https://files.catbox.moe/idezj6.avif",
          "https://files.catbox.moe/m2noy6.avif",
          "https://files.catbox.moe/x3ivlz.avif",
          "https://files.catbox.moe/untrdl.avif",
          "https://files.catbox.moe/kfhvy2.avif",
          "https://files.catbox.moe/lloxvc.avif",
          "https://files.catbox.moe/i2yunr.avif",
          "https://files.catbox.moe/rvfji0.avif",
          "https://files.catbox.moe/qe6k2n.avif",
          "https://files.catbox.moe/pznnmd.avif",
          "https://files.catbox.moe/xex6ti.avif",
          "https://files.catbox.moe/jzh2pt.avif",
          "https://files.catbox.moe/y29rag.avif",
          "https://files.catbox.moe/uzqe5y.avif",
          "https://files.catbox.moe/dwh3yx.avif",
          "https://files.catbox.moe/akdw3w.avif",
          "https://files.catbox.moe/rcsx2o.avif",
          "https://files.catbox.moe/zxafhw.avif"
        ]
      }
    },
    "5": {
      "title": "Vol 1 - Lần Bại Trận #5 | Gửi Đến Cậu, Kẻ Bội Ước",
      "volume": "1",
      "last_updated": "1747535520",
      "groups": {
        "SAM Shelter": [
          "https://files.catbox.moe/xx7nn0.avif",
          "https://files.catbox.moe/jr6twz.avif",
          "https://files.catbox.moe/zfiqgl.avif",
          "https://files.catbox.moe/28vot2.avif",
          "https://files.catbox.moe/1028bu.avif",
          "https://files.catbox.moe/1ugyyf.avif",
          "https://files.catbox.moe/w6c22s.avif",
          "https://files.catbox.moe/koa97t.avif",
          "https://files.catbox.moe/teuuku.avif",
          "https://files.catbox.moe/hf6vd9.avif",
          "https://files.catbox.moe/y8ixoz.avif",
          "https://files.catbox.moe/8zsbs7.avif",
          "https://files.catbox.moe/lto9lg.avif",
          "https://files.catbox.moe/jicq0x.avif",
          "https://files.catbox.moe/a7xyb2.avif",
          "https://files.catbox.moe/a5mrfg.avif",
          "https://files.catbox.moe/c8t2xo.avif",
          "https://files.catbox.moe/b56p3j.avif",
          "https://files.catbox.moe/sgs53c.avif",
          "https://files.catbox.moe/5mtpsj.avif",
          "https://files.catbox.moe/4oqcgi.avif",
          "https://files.catbox.moe/pd08q5.avif",
          "https://files.catbox.moe/drcpu7.avif",
          "https://files.catbox.moe/aghf2i.avif",
          "https://files.catbox.moe/lnfjyo.avif",
          "https://files.catbox.moe/0u9qpc.avif",
          "https://files.catbox.moe/ejox6n.avif",
          "https://files.catbox.moe/5vu0wm.avif",
          "https://files.catbox.moe/w6l72u.avif",
          "https://files.catbox.moe/ko6amp.avif",
          "https://files.catbox.moe/i80jxw.avif",
          "https://files.catbox.moe/o721o4.avif",
          "https://files.catbox.moe/8p50um.avif",
          "https://files.catbox.moe/464xpm.avif",
          "https://files.catbox.moe/jrffla.avif",
          "https://files.catbox.moe/olwydv.avif",
          "https://files.catbox.moe/naq80e.avif",
          "https://files.catbox.moe/bth9x0.avif",
          "https://files.catbox.moe/advek2.avif",
          "https://files.catbox.moe/keuyh1.avif"
        ]
      }
    },
    "6": {
      "title": "Vol 2 - Lần Bại Trận #6 | Nỗi Phiền Muộn Của Kaju Trong Chiến Lược Công Kích Onii-sama",
      "volume": "2",
      "last_updated": "1747535602",
      "groups": {
        "SAM Shelter": [
          "https://files.catbox.moe/985lo2.avif",
          "https://files.catbox.moe/j17asj.avif",
          "https://files.catbox.moe/3sk47h.avif",
          "https://files.catbox.moe/e6gp2e.avif",
          "https://files.catbox.moe/5qvefy.avif",
          "https://files.catbox.moe/cvpop3.avif",
          "https://files.catbox.moe/nte41g.avif",
          "https://files.catbox.moe/13e9nq.avif",
          "https://files.catbox.moe/priv9h.avif",
          "https://files.catbox.moe/1le4lo.avif",
          "https://files.catbox.moe/9x05q8.avif",
          "https://files.catbox.moe/1f1cm1.avif",
          "https://files.catbox.moe/7dxo33.avif",
          "https://files.catbox.moe/78ye63.avif",
          "https://files.catbox.moe/ujgke9.avif",
          "https://files.catbox.moe/cu4klz.avif",
          "https://files.catbox.moe/6n15q9.avif",
          "https://files.catbox.moe/dgkxqs.avif"
        ]
      }
    },
    "7": {
      "title": "Vol 2 - Lần Bại Trận #7 | Gửi Đến Cậu, Kẻ Bội Ước (Phần Tiếp Theo)",
      "volume": "2",
      "last_updated": "1747535876",
      "groups": {
        "SAM Shelter": [
          "https://files.catbox.moe/22b6px.avif",
          "https://files.catbox.moe/8q51pk.avif",
          "https://files.catbox.moe/p8vbsg.avif",
          "https://files.catbox.moe/6fmg3a.avif",
          "https://files.catbox.moe/9loanp.avif",
          "https://files.catbox.moe/17m3fb.avif",
          "https://files.catbox.moe/ixvrmk.avif",
          "https://files.catbox.moe/959h4a.avif",
          "https://files.catbox.moe/15t3xd.avif",
          "https://files.catbox.moe/g1n6bm.avif",
          "https://files.catbox.moe/z7ppak.avif",
          "https://files.catbox.moe/9g2ojv.avif",
          "https://files.catbox.moe/8am8w4.avif",
          "https://files.catbox.moe/7i78so.avif",
          "https://files.catbox.moe/tq1mvp.avif",
          "https://files.catbox.moe/se0akr.avif",
          "https://files.catbox.moe/hisrtn.avif",
          "https://files.catbox.moe/xtpjny.avif",
          "https://files.catbox.moe/gjeswt.avif",
          "https://files.catbox.moe/ipus14.avif",
          "https://files.catbox.moe/ld69qe.avif",
          "https://files.catbox.moe/iq0y27.avif",
          "https://files.catbox.moe/n26p16.avif",
          "https://files.catbox.moe/bcofr0.avif",
          "https://files.catbox.moe/rkuws2.avif",
          "https://files.catbox.moe/7wb2fa.avif",
          "https://files.catbox.moe/6d7t5q.avif",
          "https://files.catbox.moe/v33hs7.avif",
          "https://files.catbox.moe/ita0q5.avif",
          "https://files.catbox.moe/ctx8wr.avif",
          "https://files.catbox.moe/bfa565.avif",
          "https://files.catbox.moe/co0h9e.avif",
          "https://files.catbox.moe/pq1l5b.avif",
          "https://files.catbox.moe/9wfd0n.avif",
          "https://files.catbox.moe/dinau4.avif",
          "https://files.catbox.moe/zlirqe.avif",
          "https://files.catbox.moe/3tmcap.avif",
          "https://files.catbox.moe/5nh9fy.avif",
          "https://files.catbox.moe/ylx5kn.avif",
          "https://files.catbox.moe/bcj19g.avif",
          "https://files.catbox.moe/1zixvd.avif",
          "https://files.catbox.moe/k3fwxt.avif",
          "https://files.catbox.moe/1mck21.avif",
          "https://files.catbox.moe/q6j3nm.avif",
          "https://files.catbox.moe/tc9djr.avif",
          "https://files.catbox.moe/d7cama.avif",
          "https://files.catbox.moe/gz500p.avif",
          "https://files.catbox.moe/jsxz8m.avif"
        ]
      }
    },
    "8": {
      "title": "Vol 2 - Lần Bại Trận #8 | Là Thế Đấy, Nukumizu-kun",
      "volume": "2",
      "last_updated": "1747536373",
      "groups": {
        "SAM Shelter": [
          "https://files.catbox.moe/xq4w0c.avif",
          "https://files.catbox.moe/zzd3e5.avif",
          "https://files.catbox.moe/hmo3q6.avif",
          "https://files.catbox.moe/57auxp.avif",
          "https://files.catbox.moe/f2xpxi.avif",
          "https://files.catbox.moe/ixmeo4.avif",
          "https://files.catbox.moe/pj48zl.avif",
          "https://files.catbox.moe/ct67xm.avif",
          "https://files.catbox.moe/osfg27.avif",
          "https://files.catbox.moe/vt1e4h.avif",
          "https://files.catbox.moe/s731as.avif",
          "https://files.catbox.moe/q16kij.avif",
          "https://files.catbox.moe/8eu68c.avif",
          "https://files.catbox.moe/jg79d8.avif",
          "https://files.catbox.moe/1lk49l.avif",
          "https://files.catbox.moe/848d7k.avif",
          "https://files.catbox.moe/8z2kmf.avif",
          "https://files.catbox.moe/io25nc.avif",
          "https://files.catbox.moe/rstg7m.avif",
          "https://files.catbox.moe/jl30xn.avif",
          "https://files.catbox.moe/51896u.avif",
          "https://files.catbox.moe/vjhuyw.avif",
          "https://files.catbox.moe/e4g6p4.avif",
          "https://files.catbox.moe/x4yri2.avif",
          "https://files.catbox.moe/57ci5q.avif",
          "https://files.catbox.moe/c23z5m.avif",
          "https://files.catbox.moe/v8q3ag.avif",
          "https://files.catbox.moe/ocxzfy.avif",
          "https://files.catbox.moe/5m26lk.avif",
          "https://files.catbox.moe/6xluaz.avif"
        ]
      }
    },
    "9": {
      "title": "Vol 2 - Lần Bại Trận #9 | Sóng, Thi Thoảng, Remon Và Mùi Vị Của Sốt",
      "volume": "2",
      "last_updated": "1747536441",
      "groups": {
        "SAM Shelter": [
          "https://files.catbox.moe/fpjwko.avif",
          "https://files.catbox.moe/ypi9f0.avif",
          "https://files.catbox.moe/dot4xk.avif",
          "https://files.catbox.moe/nxbxj0.avif",
          "https://files.catbox.moe/q20hk4.avif",
          "https://files.catbox.moe/xc33ty.avif",
          "https://files.catbox.moe/67gly2.avif",
          "https://files.catbox.moe/7okk6r.avif",
          "https://files.catbox.moe/d48soj.avif",
          "https://files.catbox.moe/gzkqy8.avif",
          "https://files.catbox.moe/5d59v3.avif",
          "https://files.catbox.moe/0t9epq.avif",
          "https://files.catbox.moe/n2lwgu.avif",
          "https://files.catbox.moe/2oipuz.avif",
          "https://files.catbox.moe/q5slrx.avif",
          "https://files.catbox.moe/u3qakx.avif",
          "https://files.catbox.moe/j1rp5e.avif",
          "https://files.catbox.moe/0d2vm0.avif",
          "https://files.catbox.moe/w99uql.avif",
          "https://files.catbox.moe/251srr.avif",
          "https://files.catbox.moe/j64cwi.avif",
          "https://files.catbox.moe/a6s7as.avif"
        ]
      }
    },
    "10": {
      "title": "Vol 2 - Lần Bại Trận #10 | Pháo Hoa, Pháo Hoa và Lòng Bò",
      "volume": "2",
      "last_updated": "1747536579",
      "groups": {
        "SAM Shelter": [
          "https://files.catbox.moe/twirs4.avif",
          "https://files.catbox.moe/25co81.avif",
          "https://files.catbox.moe/ymesa1.avif",
          "https://files.catbox.moe/ec636n.avif",
          "https://files.catbox.moe/ktk5jg.avif",
          "https://files.catbox.moe/rfe2mm.avif",
          "https://files.catbox.moe/k5d4yz.avif",
          "https://files.catbox.moe/u1g037.avif",
          "https://files.catbox.moe/2kpfrx.avif",
          "https://files.catbox.moe/sfvlpv.avif",
          "https://files.catbox.moe/h2sojw.avif",
          "https://files.catbox.moe/f2mb4z.avif",
          "https://files.catbox.moe/qhzjm0.avif",
          "https://files.catbox.moe/hhpatj.avif",
          "https://files.catbox.moe/ewb7kd.avif",
          "https://files.catbox.moe/4ux0pk.avif",
          "https://files.catbox.moe/hz8xu6.avif",
          "https://files.catbox.moe/b6sva5.avif"
        ]
      }
    },
    "11": {
      "title": "Vol 2 - Lần Bại Trận #11 | Thất Bại Khi Trận Chiến Còn Chưa Bắt Đầu, Komari Chika Rút Lui",
      "volume": "3",
      "last_updated": "1747563451",
      "groups": {
        "SAM Shelter ": [
          "https://files.catbox.moe/tr4kvb.png",
          "https://files.catbox.moe/yv01oa.png",
          "https://files.catbox.moe/ipnjxq.png",
          "https://files.catbox.moe/zbjlc4.png",
          "https://files.catbox.moe/qw7kvz.png",
          "https://files.catbox.moe/7fkrli.png",
          "https://files.catbox.moe/xq55t7.png",
          "https://files.catbox.moe/gt4ysk.png",
          "https://files.catbox.moe/wm4p0i.png",
          "https://files.catbox.moe/rbz379.png",
          "https://files.catbox.moe/qzx08x.png",
          "https://files.catbox.moe/2wxsen.png",
          "https://files.catbox.moe/z4q5kf.png",
          "https://files.catbox.moe/pknyyl.png",
          "https://files.catbox.moe/4kojuv.png",
          "https://files.catbox.moe/r0byrf.png",
          "https://files.catbox.moe/le7skj.png",
          "https://files.catbox.moe/9ml7ub.png",
          "https://files.catbox.moe/y4xxcx.png",
          "https://files.catbox.moe/44egmy.png",
          "https://files.catbox.moe/szpw3o.png",
          "https://files.catbox.moe/cc6rgy.png",
          "https://files.catbox.moe/282tos.png",
          "https://files.catbox.moe/9anmau.png",
          "https://files.catbox.moe/eyqgbj.png",
          "https://files.catbox.moe/z18a1s.png",
          "https://files.catbox.moe/dyj6d6.png",
          "https://files.catbox.moe/2uqty1.png",
          "https://files.catbox.moe/gadz3l.png",
          "https://files.catbox.moe/l7ejn2.png",
          "https://files.catbox.moe/5a599g.png",
          "https://files.catbox.moe/czhzs0.png",
          "https://files.catbox.moe/d32o3s.png",
          "https://files.catbox.moe/coehn2.png"
        ]
      }
    },
    "12": {
      "title": "Vol 3 - Lần Bại Trận #12 | Bạn Lườm Gái Thua, Gái Thua Lườm Lại Bạn",
      "volume": "3",
      "last_updated": "1747563663",
      "groups": {
        "SAM Shelter ": [
          "https://files.catbox.moe/lzptmh.png",
          "https://files.catbox.moe/8vf67s.png",
          "https://files.catbox.moe/iec5y8.png",
          "https://files.catbox.moe/9cdix4.png",
          "https://files.catbox.moe/55adwb.png",
          "https://files.catbox.moe/164d3r.png",
          "https://files.catbox.moe/4845d9.png",
          "https://files.catbox.moe/qr4k0p.png",
          "https://files.catbox.moe/ep6c4g.png",
          "https://files.catbox.moe/lqyvxd.png",
          "https://files.catbox.moe/sw3jb9.png",
          "https://files.catbox.moe/m8j0ti.png",
          "https://files.catbox.moe/xdabsi.png",
          "https://files.catbox.moe/3nu8j2.png",
          "https://files.catbox.moe/1xpf2s.png",
          "https://files.catbox.moe/u3t8oz.png",
          "https://files.catbox.moe/nndk3l.png",
          "https://files.catbox.moe/p94umn.png",
          "https://files.catbox.moe/twt62k.png",
          "https://files.catbox.moe/dwt723.png",
          "https://files.catbox.moe/uxkz62.png",
          "https://files.catbox.moe/m07lzb.png",
          "https://files.catbox.moe/qe9a15.png",
          "https://files.catbox.moe/l4jue2.png",
          "https://files.catbox.moe/bw2wko.png",
          "https://files.catbox.moe/3lwv8o.png",
          "https://files.catbox.moe/dpuegg.png",
          "https://files.catbox.moe/37siyy.png",
          "https://files.catbox.moe/kixauh.png",
          "https://files.catbox.moe/isfdnh.png",
          "https://files.catbox.moe/5vdgm2.png"
        ]
      }
    },
    "13": {
      "title": "Vol 3 - Lần Bại Trận #13 | Vào Một Ngày Nọ, Ở Trong Khu Rừng",
      "volume": "3",
      "last_updated": "1747564234",
      "groups": {
        "SAM Shelter ": [
          "https://files.catbox.moe/i5k90n.png",
          "https://files.catbox.moe/s2tk2z.png",
          "https://files.catbox.moe/8kpy36.png",
          "https://files.catbox.moe/f59wku.png",
          "https://files.catbox.moe/osw47o.png",
          "https://files.catbox.moe/igjx4y.png",
          "https://files.catbox.moe/j0cjtd.png",
          "https://files.catbox.moe/15bzfl.png",
          "https://files.catbox.moe/xoxip9.png",
          "https://files.catbox.moe/1veubr.png",
          "https://files.catbox.moe/jozoj0.png",
          "https://files.catbox.moe/cqb23p.png",
          "https://files.catbox.moe/kp6ugr.png",
          "https://files.catbox.moe/m0w3yh.png",
          "https://files.catbox.moe/1t4p1d.png",
          "https://files.catbox.moe/qnmgvh.png",
          "https://files.catbox.moe/yrwlis.png",
          "https://files.catbox.moe/1no4ed.png",
          "https://files.catbox.moe/1i72b2.png",
          "https://files.catbox.moe/52gige.png",
          "https://files.catbox.moe/8xvlv2.png",
          "https://files.catbox.moe/f4kozi.png",
          "https://files.catbox.moe/3zcdq4.png",
          "https://files.catbox.moe/r7a5pf.png",
          "https://files.catbox.moe/a1gqqr.png",
          "https://files.catbox.moe/ana8fq.png",
          "https://files.catbox.moe/kidw2x.png"
        ]
      }
    },
    "14": {
      "title": "Vol 3 - Lần Bại Trận #14 | Chú Chim Xanh Của Sự Hạnh Phúc",
      "volume": "3",
      "last_updated": "1747564625",
      "groups": {
        "SAM Shelter ": [
          "https://files.catbox.moe/gtlkps.png",
          "https://files.catbox.moe/gga8dd.png",
          "https://files.catbox.moe/au1chi.png",
          "https://files.catbox.moe/nxng16.png",
          "https://files.catbox.moe/tt9agu.png",
          "https://files.catbox.moe/u6sk3v.png",
          "https://files.catbox.moe/8j9lli.png",
          "https://files.catbox.moe/5ee98m.png",
          "https://files.catbox.moe/nh5mx9.png",
          "https://files.catbox.moe/2apin6.png",
          "https://files.catbox.moe/k8qp7b.png",
          "https://files.catbox.moe/stis1q.png",
          "https://files.catbox.moe/6tu50a.png",
          "https://files.catbox.moe/4yf2cg.png",
          "https://files.catbox.moe/aibf9n.png",
          "https://files.catbox.moe/dgdelb.png",
          "https://files.catbox.moe/myg9h6.png",
          "https://files.catbox.moe/pfxne0.png",
          "https://files.catbox.moe/jj5ivp.png",
          "https://files.catbox.moe/8qupws.png",
          "https://files.catbox.moe/4u6nvr.png",
          "https://files.catbox.moe/b00xu1.png",
          "https://files.catbox.moe/z5m5uc.png",
          "https://files.catbox.moe/8ojoyj.png",
          "https://files.catbox.moe/69rmv0.png",
          "https://files.catbox.moe/zg7t7n.png",
          "https://files.catbox.moe/xth4wp.png",
          "https://files.catbox.moe/g6y9on.png",
          "https://files.catbox.moe/bd3nx0.png",
          "https://files.catbox.moe/4shksr.png",
          "https://files.catbox.moe/jho859.png",
          "https://files.catbox.moe/47hd1n.png",
          "https://files.catbox.moe/f8oz69.png",
          "https://files.catbox.moe/ea6rwx.png",
          "https://files.catbox.moe/uubsk3.png",
          "https://files.catbox.moe/plss1l.png",
          "https://files.catbox.moe/0e12fz.png",
          "https://files.catbox.moe/3psdru.png",
          "https://files.catbox.moe/zxuor7.png",
          "https://files.catbox.moe/e4jwdp.png",
          "https://files.catbox.moe/8ti9d3.png",
          "https://files.catbox.moe/bk6w5g.png",
          "https://files.catbox.moe/0a1o0s.png",
          "https://files.catbox.moe/m36d2z.png",
          "https://files.catbox.moe/qvqetu.png",
          "https://files.catbox.moe/6n79uj.png",
          "https://files.catbox.moe/gyq1fq.png",
          "https://files.catbox.moe/bge4uv.png",
          "https://files.catbox.moe/dhpqp4.png",
          "https://files.catbox.moe/k5h2z1.png",
          "https://files.catbox.moe/x2jj3d.png",
          "https://files.catbox.moe/ykz3aw.png",
          "https://files.catbox.moe/99614u.png",
          "https://files.catbox.moe/4t8q9m.png",
          "https://files.catbox.moe/gomb5h.png",
          "https://files.catbox.moe/13ctsh.png",
          "https://files.catbox.moe/d7c9fw.png",
          "https://files.catbox.moe/dnorib.png",
          "https://files.catbox.moe/jh13ay.png",
          "https://files.catbox.moe/mucvkx.png"
        ]
      }
    }
  }
}